cfbpy/__init__.py
cfbpy/cfb.py
cfbpy/directory.py
cfbpy-0.0.3.dist-info/METADATA
cfbpy-0.0.3.dist-info/WHEEL
cfbpy-0.0.3.dist-info/licenses/LICENSE
cfbpy-0.0.3.dist-info/RECORD
