Metadata-Version: 2.3
Name: cfbpy
Version: 0.0.3
Summary: Python module for compressing/decompressing compound file binary format (CFB)
Project-URL: Homepage, https://github.com/killerwhalee/cfbpy
Project-URL: Issues, https://github.com/killerwhalee/cfbpy/issues
Author-email: killerwhalee <killerwhalee@kaist.ac.kr>
License-File: LICENSE
Classifier: License :: OSI Approved :: MIT License
Classifier: Operating System :: OS Independent
Classifier: Programming Language :: Python :: 3
Requires-Python: >=3.12
